absolidix_client/__init__.py
absolidix_client/absolidix.py
absolidix_client/absolidix_async.py
absolidix_client/client.py
absolidix_client/compat.py
absolidix_client/const.py
absolidix_client/exc.py
absolidix_client/helpers.py
absolidix_client/dtos/__init__.py
absolidix_client/dtos/auth.py
absolidix_client/dtos/base.py
absolidix_client/dtos/calculation.py
absolidix_client/dtos/collection.py
absolidix_client/dtos/datasource.py
absolidix_client/dtos/error.py
absolidix_client/dtos/event.py
absolidix_client/dtos/resp.py
absolidix_client/dtos/user.py
absolidix_client/models/__init__.py
absolidix_client/models/auth.py
absolidix_client/models/base.py
absolidix_client/models/event.py
absolidix_client/models/hub.py
absolidix_client/models/subscription.py
absolidix_client/namespaces/__init__.py
absolidix_client/namespaces/base.py
absolidix_client/namespaces/calculations.py
absolidix_client/namespaces/root.py
absolidix_client/namespaces/stream.py
absolidix_client/namespaces/v0.py
absolidix_client/namespaces/v0_auth.py
absolidix_client/namespaces/v0_calculations.py
absolidix_client/namespaces/v0_collections.py
absolidix_client/namespaces/v0_datasources.py
absolidix_client-0.8.4.dist-info/licenses/LICENSE
absolidix_client-0.8.4.dist-info/METADATA
absolidix_client-0.8.4.dist-info/WHEEL
absolidix_client-0.8.4.dist-info/top_level.txt
absolidix_client-0.8.4.dist-info/RECORD
