Metadata-Version: 2.4
Name: absolidix-client
Version: 0.8.4
Summary: Absolidix infra API client in Python
Author-email: Sergei Korolev <knopki@duck.com>
License-Expression: BSD-3-Clause
Project-URL: Home, https://bitbucket.org/tilde-mi/absolidix-client
Project-URL: Changelog, https://bitbucket.org/tilde-mi/absolidix-client/blob/master/CHANGELOG.md
Project-URL: Issues, https://bitbucket.org/tilde-mi/absolidix-client/issues
Project-URL: Source, https://bitbucket.org/tilde-mi/absolidix-client
Keywords: absolidix,client
Classifier: Development Status :: 4 - Beta
Classifier: Intended Audience :: Science/Research
Classifier: Operating System :: OS Independent
Classifier: Programming Language :: Python
Classifier: Programming Language :: Python :: 3
Classifier: Programming Language :: Python :: 3.9
Classifier: Programming Language :: Python :: 3.10
Classifier: Programming Language :: Python :: 3.11
Classifier: Programming Language :: Python :: 3.12
Classifier: Programming Language :: Python :: 3.13
Classifier: Topic :: Scientific/Engineering
Classifier: Topic :: Scientific/Engineering :: Chemistry
Classifier: Topic :: Scientific/Engineering :: Physics
Classifier: Topic :: Scientific/Engineering :: Information Analysis
Requires-Python: >=3.9
License-File: LICENSE
Requires-Dist: aiohttp>=3.7.4
Requires-Dist: aiohttp-sse-client>=0.2.1
Requires-Dist: typing-extensions>=4.2.0; python_version < "3.11"
Requires-Dist: yarl>=1.6.3
Provides-Extra: dev
Requires-Dist: build; extra == "dev"
Requires-Dist: commitizen; extra == "dev"
Requires-Dist: freezegun; extra == "dev"
Requires-Dist: pyright; extra == "dev"
Requires-Dist: pytest-aiohttp<2,>=1.0.4; extra == "dev"
Requires-Dist: pytest-asyncio; extra == "dev"
Requires-Dist: pytest-cov; extra == "dev"
Requires-Dist: pyupgrade; extra == "dev"
Requires-Dist: ruff; extra == "dev"
Requires-Dist: twine; extra == "dev"
Requires-Dist: wdb; extra == "dev"
Dynamic: license-file
